library/__init__.py
library/hwidfinder.py
hwidfinder-0.0.2.dist-info/METADATA
hwidfinder-0.0.2.dist-info/WHEEL
hwidfinder-0.0.2.dist-info/top_level.txt
hwidfinder-0.0.2.dist-info/RECORD
