Metadata-Version: 2.1
Name: hwidfinder
Version: 0.0.2
Summary: Find your HWID easily.
Home-page: UNKNOWN
Author: Arxify (Daniel Rodriguez)
Author-email: <arxifybusiness@proton.me>
License: UNKNOWN
Keywords: python,hwid,finder,find,windows,tool
Platform: UNKNOWN
Classifier: Development Status :: 1 - Planning
Classifier: Intended Audience :: Developers
Classifier: Programming Language :: Python :: 3
Classifier: Operating System :: Unix
Classifier: Operating System :: MacOS :: MacOS X
Classifier: Operating System :: Microsoft :: Windows
Requires-Dist: colorama
